{"v":3,"stories":{"configure-your-project--docs":{"id":"configure-your-project--docs","title":"Configure your project","name":"Docs","importPath":"./src/stories/Configure.mdx","storiesImports":[],"tags":["unattached-mdx","docs"],"kind":"Configure your project","story":"Docs","parameters":{"__id":"configure-your-project--docs","docsOnly":true,"fileName":"./src/stories/Configure.mdx"}},"articlecard--docs":{"id":"articlecard--docs","title":"ArticleCard","name":"Docs","importPath":"./src/components/ArticleCard.stories.tsx","tags":["autodocs","docs"],"storiesImports":[],"kind":"ArticleCard","story":"Docs","parameters":{"__id":"articlecard--docs","docsOnly":true,"fileName":"./src/components/ArticleCard.stories.tsx"}},"articlecard--base":{"id":"articlecard--base","name":"Base","title":"ArticleCard","importPath":"./src/components/ArticleCard.stories.tsx","tags":["autodocs","story"],"kind":"ArticleCard","story":"Base","parameters":{"__id":"articlecard--base","docsOnly":false,"fileName":"./src/components/ArticleCard.stories.tsx"}},"avatar--docs":{"id":"avatar--docs","title":"Avatar","name":"Docs","importPath":"./src/components/Avatar.stories.tsx","tags":["autodocs","docs"],"storiesImports":[],"kind":"Avatar","story":"Docs","parameters":{"__id":"avatar--docs","docsOnly":true,"fileName":"./src/components/Avatar.stories.tsx"}},"avatar--base":{"id":"avatar--base","name":"Base","title":"Avatar","importPath":"./src/components/Avatar.stories.tsx","tags":["autodocs","story"],"kind":"Avatar","story":"Base","parameters":{"__id":"avatar--base","docsOnly":false,"fileName":"./src/components/Avatar.stories.tsx"}},"avatar--name":{"id":"avatar--name","name":"Name","title":"Avatar","importPath":"./src/components/Avatar.stories.tsx","tags":["autodocs","story"],"kind":"Avatar","story":"Name","parameters":{"__id":"avatar--name","docsOnly":false,"fileName":"./src/components/Avatar.stories.tsx"}},"bignumbers--docs":{"id":"bignumbers--docs","title":"BigNumbers","name":"Docs","importPath":"./src/components/BigNumbers.stories.tsx","tags":["autodocs","docs"],"storiesImports":[],"kind":"BigNumbers","story":"Docs","parameters":{"__id":"bignumbers--docs","docsOnly":true,"fileName":"./src/components/BigNumbers.stories.tsx"}},"bignumbers--base":{"id":"bignumbers--base","name":"Base","title":"BigNumbers","importPath":"./src/components/BigNumbers.stories.tsx","tags":["autodocs","story"],"kind":"BigNumbers","story":"Base","parameters":{"__id":"bignumbers--base","docsOnly":false,"fileName":"./src/components/BigNumbers.stories.tsx"}},"categorytabs--docs":{"id":"categorytabs--docs","title":"CategoryTabs","name":"Docs","importPath":"./src/components/CategoryTabs.stories.tsx","tags":["autodocs","docs"],"storiesImports":[],"kind":"CategoryTabs","story":"Docs","parameters":{"__id":"categorytabs--docs","docsOnly":true,"fileName":"./src/components/CategoryTabs.stories.tsx"}},"categorytabs--base":{"id":"categorytabs--base","name":"Base","title":"CategoryTabs","importPath":"./src/components/CategoryTabs.stories.tsx","tags":["autodocs","story"],"kind":"CategoryTabs","story":"Base","parameters":{"__id":"categorytabs--base","docsOnly":false,"fileName":"./src/components/CategoryTabs.stories.tsx"}},"contactblock--docs":{"id":"contactblock--docs","title":"ContactBlock","name":"Docs","importPath":"./src/components/ContactBlock.stories.tsx","tags":["autodocs","docs"],"storiesImports":[],"kind":"ContactBlock","story":"Docs","parameters":{"__id":"contactblock--docs","docsOnly":true,"fileName":"./src/components/ContactBlock.stories.tsx"}},"contactblock--base":{"id":"contactblock--base","name":"Base","title":"ContactBlock","importPath":"./src/components/ContactBlock.stories.tsx","tags":["autodocs","story"],"kind":"ContactBlock","story":"Base","parameters":{"__id":"contactblock--base","docsOnly":false,"fileName":"./src/components/ContactBlock.stories.tsx"}},"contentblock--docs":{"id":"contentblock--docs","title":"ContentBlock","name":"Docs","importPath":"./src/components/ContentBlock.stories.tsx","tags":["autodocs","docs"],"storiesImports":[],"kind":"ContentBlock","story":"Docs","parameters":{"__id":"contentblock--docs","docsOnly":true,"fileName":"./src/components/ContentBlock.stories.tsx"}},"contentblock--left":{"id":"contentblock--left","name":"Left","title":"ContentBlock","importPath":"./src/components/ContentBlock.stories.tsx","tags":["autodocs","story"],"kind":"ContentBlock","story":"Left","parameters":{"__id":"contentblock--left","docsOnly":false,"fileName":"./src/components/ContentBlock.stories.tsx"}},"contentblock--center":{"id":"contentblock--center","name":"Center","title":"ContentBlock","importPath":"./src/components/ContentBlock.stories.tsx","tags":["autodocs","story"],"kind":"ContentBlock","story":"Center","parameters":{"__id":"contentblock--center","docsOnly":false,"fileName":"./src/components/ContentBlock.stories.tsx"}},"contentblock--right":{"id":"contentblock--right","name":"Right","title":"ContentBlock","importPath":"./src/components/ContentBlock.stories.tsx","tags":["autodocs","story"],"kind":"ContentBlock","story":"Right","parameters":{"__id":"contentblock--right","docsOnly":false,"fileName":"./src/components/ContentBlock.stories.tsx"}},"footer--docs":{"id":"footer--docs","title":"Footer","name":"Docs","importPath":"./src/components/Footer.stories.tsx","tags":["autodocs","docs"],"storiesImports":[],"kind":"Footer","story":"Docs","parameters":{"__id":"footer--docs","docsOnly":true,"fileName":"./src/components/Footer.stories.tsx"}},"footer--base":{"id":"footer--base","name":"Base","title":"Footer","importPath":"./src/components/Footer.stories.tsx","tags":["autodocs","story"],"kind":"Footer","story":"Base","parameters":{"__id":"footer--base","docsOnly":false,"fileName":"./src/components/Footer.stories.tsx"}},"fourcolumns--docs":{"id":"fourcolumns--docs","title":"FourColumns","name":"Docs","importPath":"./src/components/FourColumns.stories.tsx","tags":["autodocs","docs"],"storiesImports":[],"kind":"FourColumns","story":"Docs","parameters":{"__id":"fourcolumns--docs","docsOnly":true,"fileName":"./src/components/FourColumns.stories.tsx"}},"fourcolumns--base":{"id":"fourcolumns--base","name":"Base","title":"FourColumns","importPath":"./src/components/FourColumns.stories.tsx","tags":["autodocs","story"],"kind":"FourColumns","story":"Base","parameters":{"__id":"fourcolumns--base","docsOnly":false,"fileName":"./src/components/FourColumns.stories.tsx"}},"illustration--docs":{"id":"illustration--docs","title":"Illustration","name":"Docs","importPath":"./src/components/Illustration.stories.tsx","tags":["autodocs","docs"],"storiesImports":[],"kind":"Illustration","story":"Docs","parameters":{"__id":"illustration--docs","docsOnly":true,"fileName":"./src/components/Illustration.stories.tsx"}},"illustration--base":{"id":"illustration--base","name":"Base","title":"Illustration","importPath":"./src/components/Illustration.stories.tsx","tags":["autodocs","story"],"kind":"Illustration","story":"Base","parameters":{"__id":"illustration--base","docsOnly":false,"fileName":"./src/components/Illustration.stories.tsx"}},"logo--docs":{"id":"logo--docs","title":"Logo","name":"Docs","importPath":"./src/components/Logo.stories.tsx","tags":["autodocs","docs"],"storiesImports":[],"kind":"Logo","story":"Docs","parameters":{"__id":"logo--docs","docsOnly":true,"fileName":"./src/components/Logo.stories.tsx"}},"logo--base":{"id":"logo--base","name":"Base","title":"Logo","importPath":"./src/components/Logo.stories.tsx","tags":["autodocs","story"],"kind":"Logo","story":"Base","parameters":{"__id":"logo--base","docsOnly":false,"fileName":"./src/components/Logo.stories.tsx"}},"logo--wordmark":{"id":"logo--wordmark","name":"Wordmark","title":"Logo","importPath":"./src/components/Logo.stories.tsx","tags":["autodocs","story"],"kind":"Logo","story":"Wordmark","parameters":{"__id":"logo--wordmark","docsOnly":false,"fileName":"./src/components/Logo.stories.tsx"}},"logowall--docs":{"id":"logowall--docs","title":"LogoWall","name":"Docs","importPath":"./src/components/LogoWall.stories.tsx","tags":["autodocs","docs"],"storiesImports":[],"kind":"LogoWall","story":"Docs","parameters":{"__id":"logowall--docs","docsOnly":true,"fileName":"./src/components/LogoWall.stories.tsx"}},"logowall--base":{"id":"logowall--base","name":"Base","title":"LogoWall","importPath":"./src/components/LogoWall.stories.tsx","tags":["autodocs","story"],"kind":"LogoWall","story":"Base","parameters":{"__id":"logowall--base","docsOnly":false,"fileName":"./src/components/LogoWall.stories.tsx"}},"navbar--docs":{"id":"navbar--docs","title":"Navbar","name":"Docs","importPath":"./src/components/Navbar.stories.tsx","tags":["autodocs","docs"],"storiesImports":[],"kind":"Navbar","story":"Docs","parameters":{"__id":"navbar--docs","docsOnly":true,"fileName":"./src/components/Navbar.stories.tsx"}},"navbar--base":{"id":"navbar--base","name":"Base","title":"Navbar","importPath":"./src/components/Navbar.stories.tsx","tags":["autodocs","story"],"kind":"Navbar","story":"Base","parameters":{"__id":"navbar--base","docsOnly":false,"fileName":"./src/components/Navbar.stories.tsx"}},"navigationblock--docs":{"id":"navigationblock--docs","title":"NavigationBlock","name":"Docs","importPath":"./src/components/NavigationBlock.stories.tsx","tags":["autodocs","docs"],"storiesImports":[],"kind":"NavigationBlock","story":"Docs","parameters":{"__id":"navigationblock--docs","docsOnly":true,"fileName":"./src/components/NavigationBlock.stories.tsx"}},"navigationblock--base":{"id":"navigationblock--base","name":"Base","title":"NavigationBlock","importPath":"./src/components/NavigationBlock.stories.tsx","tags":["autodocs","story"],"kind":"NavigationBlock","story":"Base","parameters":{"__id":"navigationblock--base","docsOnly":false,"fileName":"./src/components/NavigationBlock.stories.tsx"}},"teamimage--docs":{"id":"teamimage--docs","title":"TeamImage","name":"Docs","importPath":"./src/components/TeamImage.stories.tsx","tags":["autodocs","docs"],"storiesImports":[],"kind":"TeamImage","story":"Docs","parameters":{"__id":"teamimage--docs","docsOnly":true,"fileName":"./src/components/TeamImage.stories.tsx"}},"teamimage--base":{"id":"teamimage--base","name":"Base","title":"TeamImage","importPath":"./src/components/TeamImage.stories.tsx","tags":["autodocs","story"],"kind":"TeamImage","story":"Base","parameters":{"__id":"teamimage--base","docsOnly":false,"fileName":"./src/components/TeamImage.stories.tsx"}},"twocolumns--docs":{"id":"twocolumns--docs","title":"TwoColumns","name":"Docs","importPath":"./src/components/TwoColumns.stories.tsx","tags":["autodocs","docs"],"storiesImports":[],"kind":"TwoColumns","story":"Docs","parameters":{"__id":"twocolumns--docs","docsOnly":true,"fileName":"./src/components/TwoColumns.stories.tsx"}},"twocolumns--base":{"id":"twocolumns--base","name":"Base","title":"TwoColumns","importPath":"./src/components/TwoColumns.stories.tsx","tags":["autodocs","story"],"kind":"TwoColumns","story":"Base","parameters":{"__id":"twocolumns--base","docsOnly":false,"fileName":"./src/components/TwoColumns.stories.tsx"}},"article-aboutauthor--docs":{"id":"article-aboutauthor--docs","title":"Article/AboutAuthor","name":"Docs","importPath":"./src/components/article/AboutAuthor.stories.tsx","tags":["autodocs","docs"],"storiesImports":[],"kind":"Article/AboutAuthor","story":"Docs","parameters":{"__id":"article-aboutauthor--docs","docsOnly":true,"fileName":"./src/components/article/AboutAuthor.stories.tsx"}},"article-aboutauthor--base":{"id":"article-aboutauthor--base","name":"Base","title":"Article/AboutAuthor","importPath":"./src/components/article/AboutAuthor.stories.tsx","tags":["autodocs","story"],"kind":"Article/AboutAuthor","story":"Base","parameters":{"__id":"article-aboutauthor--base","docsOnly":false,"fileName":"./src/components/article/AboutAuthor.stories.tsx"}},"pages-article--base":{"id":"pages-article--base","name":"Base","title":"Pages/Article","importPath":"./src/components/article/Article.stories.tsx","tags":["story"],"kind":"Pages/Article","story":"Base","parameters":{"__id":"pages-article--base","docsOnly":false,"fileName":"./src/components/article/Article.stories.tsx"}},"article-header--docs":{"id":"article-header--docs","title":"Article/Header","name":"Docs","importPath":"./src/components/article/Header.stories.tsx","tags":["autodocs","docs"],"storiesImports":[],"kind":"Article/Header","story":"Docs","parameters":{"__id":"article-header--docs","docsOnly":true,"fileName":"./src/components/article/Header.stories.tsx"}},"article-header--base":{"id":"article-header--base","name":"Base","title":"Article/Header","importPath":"./src/components/article/Header.stories.tsx","tags":["autodocs","story"],"kind":"Article/Header","story":"Base","parameters":{"__id":"article-header--base","docsOnly":false,"fileName":"./src/components/article/Header.stories.tsx"}},"article-prose--docs":{"id":"article-prose--docs","title":"Article/Prose","name":"Docs","importPath":"./src/components/article/Prose.stories.tsx","tags":["autodocs","docs"],"storiesImports":[],"kind":"Article/Prose","story":"Docs","parameters":{"__id":"article-prose--docs","docsOnly":true,"fileName":"./src/components/article/Prose.stories.tsx"}},"article-prose--base":{"id":"article-prose--base","name":"Base","title":"Article/Prose","importPath":"./src/components/article/Prose.stories.tsx","tags":["autodocs","story"],"kind":"Article/Prose","story":"Base","parameters":{"__id":"article-prose--base","docsOnly":false,"fileName":"./src/components/article/Prose.stories.tsx"}},"article-relatedarticles--docs":{"id":"article-relatedarticles--docs","title":"Article/RelatedArticles","name":"Docs","importPath":"./src/components/article/RelatedArticles.stories.tsx","tags":["autodocs","docs"],"storiesImports":[],"kind":"Article/RelatedArticles","story":"Docs","parameters":{"__id":"article-relatedarticles--docs","docsOnly":true,"fileName":"./src/components/article/RelatedArticles.stories.tsx"}},"article-relatedarticles--base":{"id":"article-relatedarticles--base","name":"Base","title":"Article/RelatedArticles","importPath":"./src/components/article/RelatedArticles.stories.tsx","tags":["autodocs","story"],"kind":"Article/RelatedArticles","story":"Base","parameters":{"__id":"article-relatedarticles--base","docsOnly":false,"fileName":"./src/components/article/RelatedArticles.stories.tsx"}},"article-sidebarlinks--docs":{"id":"article-sidebarlinks--docs","title":"Article/SidebarLinks","name":"Docs","importPath":"./src/components/article/SidebarLinks.stories.tsx","tags":["autodocs","docs"],"storiesImports":[],"kind":"Article/SidebarLinks","story":"Docs","parameters":{"__id":"article-sidebarlinks--docs","docsOnly":true,"fileName":"./src/components/article/SidebarLinks.stories.tsx"}},"article-sidebarlinks--base":{"id":"article-sidebarlinks--base","name":"Base","title":"Article/SidebarLinks","importPath":"./src/components/article/SidebarLinks.stories.tsx","tags":["autodocs","story"],"kind":"Article/SidebarLinks","story":"Base","parameters":{"__id":"article-sidebarlinks--base","docsOnly":false,"fileName":"./src/components/article/SidebarLinks.stories.tsx"}},"article-socialshare--docs":{"id":"article-socialshare--docs","title":"Article/SocialShare","name":"Docs","importPath":"./src/components/article/SocialShare.stories.tsx","tags":["autodocs","docs"],"storiesImports":[],"kind":"Article/SocialShare","story":"Docs","parameters":{"__id":"article-socialshare--docs","docsOnly":true,"fileName":"./src/components/article/SocialShare.stories.tsx"}},"article-socialshare--base":{"id":"article-socialshare--base","name":"Base","title":"Article/SocialShare","importPath":"./src/components/article/SocialShare.stories.tsx","tags":["autodocs","story"],"kind":"Article/SocialShare","story":"Base","parameters":{"__id":"article-socialshare--base","docsOnly":false,"fileName":"./src/components/article/SocialShare.stories.tsx"}},"bigtext--docs":{"id":"bigtext--docs","title":"BigText","name":"Docs","importPath":"./src/components/bigtext/BigText.stories.tsx","tags":["autodocs","docs"],"storiesImports":[],"kind":"BigText","story":"Docs","parameters":{"__id":"bigtext--docs","docsOnly":true,"fileName":"./src/components/bigtext/BigText.stories.tsx"}},"bigtext--base":{"id":"bigtext--base","name":"Base","title":"BigText","importPath":"./src/components/bigtext/BigText.stories.tsx","tags":["autodocs","story"],"kind":"BigText","story":"Base","parameters":{"__id":"bigtext--base","docsOnly":false,"fileName":"./src/components/bigtext/BigText.stories.tsx"}},"bigtext--subheading":{"id":"bigtext--subheading","name":"Subheading","title":"BigText","importPath":"./src/components/bigtext/BigText.stories.tsx","tags":["autodocs","story"],"kind":"BigText","story":"Subheading","parameters":{"__id":"bigtext--subheading","docsOnly":false,"fileName":"./src/components/bigtext/BigText.stories.tsx"}},"bigtext--author":{"id":"bigtext--author","name":"Author","title":"BigText","importPath":"./src/components/bigtext/BigText.stories.tsx","tags":["autodocs","story"],"kind":"BigText","story":"Author","parameters":{"__id":"bigtext--author","docsOnly":false,"fileName":"./src/components/bigtext/BigText.stories.tsx"}},"ui-button--docs":{"id":"ui-button--docs","title":"ui/Button","name":"Docs","importPath":"./src/components/ui/button/button.stories.tsx","tags":["autodocs","docs"],"storiesImports":[],"kind":"ui/Button","story":"Docs","parameters":{"__id":"ui-button--docs","docsOnly":true,"fileName":"./src/components/ui/button/button.stories.tsx"}},"ui-button--base":{"id":"ui-button--base","name":"Base","title":"ui/Button","importPath":"./src/components/ui/button/button.stories.tsx","tags":["autodocs","story"],"kind":"ui/Button","story":"Base","parameters":{"__id":"ui-button--base","docsOnly":false,"fileName":"./src/components/ui/button/button.stories.tsx"}},"ui-button--long-text":{"id":"ui-button--long-text","name":"Long Text","title":"ui/Button","importPath":"./src/components/ui/button/button.stories.tsx","tags":["autodocs","story"],"kind":"ui/Button","story":"Long Text","parameters":{"__id":"ui-button--long-text","docsOnly":false,"fileName":"./src/components/ui/button/button.stories.tsx"}},"ui-button--cta":{"id":"ui-button--cta","name":"CTA","title":"ui/Button","importPath":"./src/components/ui/button/button.stories.tsx","tags":["autodocs","story"],"kind":"ui/Button","story":"CTA","parameters":{"__id":"ui-button--cta","docsOnly":false,"fileName":"./src/components/ui/button/button.stories.tsx"}},"example-button--docs":{"id":"example-button--docs","title":"Example/Button","name":"Docs","importPath":"./src/stories/Button.stories.ts","tags":["autodocs","docs"],"storiesImports":[],"kind":"Example/Button","story":"Docs","parameters":{"__id":"example-button--docs","docsOnly":true,"fileName":"./src/stories/Button.stories.ts"}},"example-button--primary":{"id":"example-button--primary","name":"Primary","title":"Example/Button","importPath":"./src/stories/Button.stories.ts","tags":["autodocs","story"],"kind":"Example/Button","story":"Primary","parameters":{"__id":"example-button--primary","docsOnly":false,"fileName":"./src/stories/Button.stories.ts"}},"example-button--secondary":{"id":"example-button--secondary","name":"Secondary","title":"Example/Button","importPath":"./src/stories/Button.stories.ts","tags":["autodocs","story"],"kind":"Example/Button","story":"Secondary","parameters":{"__id":"example-button--secondary","docsOnly":false,"fileName":"./src/stories/Button.stories.ts"}},"example-button--large":{"id":"example-button--large","name":"Large","title":"Example/Button","importPath":"./src/stories/Button.stories.ts","tags":["autodocs","story"],"kind":"Example/Button","story":"Large","parameters":{"__id":"example-button--large","docsOnly":false,"fileName":"./src/stories/Button.stories.ts"}},"example-button--small":{"id":"example-button--small","name":"Small","title":"Example/Button","importPath":"./src/stories/Button.stories.ts","tags":["autodocs","story"],"kind":"Example/Button","story":"Small","parameters":{"__id":"example-button--small","docsOnly":false,"fileName":"./src/stories/Button.stories.ts"}},"example-header--docs":{"id":"example-header--docs","title":"Example/Header","name":"Docs","importPath":"./src/stories/Header.stories.ts","tags":["autodocs","docs"],"storiesImports":[],"kind":"Example/Header","story":"Docs","parameters":{"__id":"example-header--docs","docsOnly":true,"fileName":"./src/stories/Header.stories.ts"}},"example-header--logged-in":{"id":"example-header--logged-in","name":"Logged In","title":"Example/Header","importPath":"./src/stories/Header.stories.ts","tags":["autodocs","story"],"kind":"Example/Header","story":"Logged In","parameters":{"__id":"example-header--logged-in","docsOnly":false,"fileName":"./src/stories/Header.stories.ts"}},"example-header--logged-out":{"id":"example-header--logged-out","name":"Logged Out","title":"Example/Header","importPath":"./src/stories/Header.stories.ts","tags":["autodocs","story"],"kind":"Example/Header","story":"Logged Out","parameters":{"__id":"example-header--logged-out","docsOnly":false,"fileName":"./src/stories/Header.stories.ts"}},"example-page--logged-out":{"id":"example-page--logged-out","name":"Logged Out","title":"Example/Page","importPath":"./src/stories/Page.stories.ts","tags":["story"],"kind":"Example/Page","story":"Logged Out","parameters":{"__id":"example-page--logged-out","docsOnly":false,"fileName":"./src/stories/Page.stories.ts"}},"example-page--logged-in":{"id":"example-page--logged-in","name":"Logged In","title":"Example/Page","importPath":"./src/stories/Page.stories.ts","tags":["play-fn","story"],"kind":"Example/Page","story":"Logged In","parameters":{"__id":"example-page--logged-in","docsOnly":false,"fileName":"./src/stories/Page.stories.ts"}}}}
